torchutils/__init__.py
torchutils/skeletons/__init__.py
torchutils/skeletons/base_log.py
torchutils/skeletons/base_memory.py
torchutils/skeletons/base_register.py
torchutils/skeletons/base_ring_buffer.py
torchutils/skeletons/base_trainer.py
torchutils/trainer/NNtrainer.py
torchutils/trainer/__init__.py
convinence_torch-1.0.0.dist-info/LICENSE
convinence_torch-1.0.0.dist-info/METADATA
convinence_torch-1.0.0.dist-info/WHEEL
convinence_torch-1.0.0.dist-info/top_level.txt
convinence_torch-1.0.0.dist-info/RECORD
