Metadata-Version: 2.1
Name: convinence-torch
Version: 1.0.0
Summary: minimalistic convenience utilities for using PyTorch
Home-page: https://github.com/NISCHALPI/ConvinenceTorch
Author: Nischal Bhattarai
Author-email: Nischal bhattarai <nischalbhattaraipi@gmail.com>
License: MIT License
Project-URL: Homepage, https://github.com/NISCHALPI/ConvinenceTorch
Keywords: torch,utilities,trainer,neural network
Classifier: License :: OSI Approved :: MIT License
Classifier: Environment :: GPU :: NVIDIA CUDA :: 11.7
Classifier: Programming Language :: Python :: 3
Classifier: Topic :: Scientific/Engineering :: Artificial Intelligence
Classifier: Topic :: Software Development :: Libraries :: Python Modules
Classifier: Topic :: Utilities
Requires-Python: >=3.8
License-File: LICENSE
Requires-Dist: torch (>=2.0.0)
Requires-Dist: scikit-learn (>=1.0)
Requires-Dist: matplotlib
Requires-Dist: tqdm
Requires-Dist: pandas
Provides-Extra: dev
Requires-Dist: nvitop ; extra == 'dev'
Requires-Dist: ruff ; extra == 'dev'
Requires-Dist: black ; extra == 'dev'
Requires-Dist: mypy ; extra == 'dev'
Requires-Dist: pytest ; extra == 'dev'
Provides-Extra: doc
Requires-Dist: sphinx ; extra == 'doc'
Requires-Dist: myst-parser ; extra == 'doc'
Requires-Dist: sphinx-rtd-theme ; extra == 'doc'
Requires-Dist: nbsphinx ; extra == 'doc'
